cdk_cloudformation_awscommunity_resource_lookup/__init__.py
cdk_cloudformation_awscommunity_resource_lookup/py.typed
cdk_cloudformation_awscommunity_resource_lookup/_jsii/__init__.py
cdk_cloudformation_awscommunity_resource_lookup/_jsii/awscommunity-resource-lookup@1.10.0-alpha.7.jsii.tgz
cdk_cloudformation_awscommunity_resource_lookup-1.10.0a7.dist-info/LICENSE
cdk_cloudformation_awscommunity_resource_lookup-1.10.0a7.dist-info/METADATA
cdk_cloudformation_awscommunity_resource_lookup-1.10.0a7.dist-info/WHEEL
cdk_cloudformation_awscommunity_resource_lookup-1.10.0a7.dist-info/top_level.txt
cdk_cloudformation_awscommunity_resource_lookup-1.10.0a7.dist-info/RECORD
