Metadata-Version: 2.1
Name: cdk-cloudformation-awscommunity-resource-lookup
Version: 1.10.0a7
Summary: This resource uses AWS Cloud Control API to perform a lookup of a resource of a given type (such as, `AWS::EC2::VPC`) in your AWS account and current region, based on a query you specify.  If only one match is found, this resource returns the primary ID of the resource (in the `AWS::EC2::VPC` example, the VPC ID) and the resource properties, that you can then reference in your template with the `Fn::GetAtt` intrinsic function.  Specify resource type search targets that are supported by 
Home-page: https://github.com/aws-cloudformation/community-registry-extensions/blob/main/resources/Resource_Lookup/README.md
Author: Amazon Web Services
License: Apache-2.0
Project-URL: Source, https://github.com/cdklabs/cdk-cloudformation.git
Classifier: Intended Audience :: Developers
Classifier: Operating System :: OS Independent
Classifier: Programming Language :: JavaScript
Classifier: Programming Language :: Python :: 3 :: Only
Classifier: Programming Language :: Python :: 3.8
Classifier: Programming Language :: Python :: 3.9
Classifier: Programming Language :: Python :: 3.10
Classifier: Programming Language :: Python :: 3.11
Classifier: Typing :: Typed
Classifier: License :: OSI Approved
Requires-Python: ~=3.8
License-File: LICENSE
Requires-Dist: aws-cdk-lib <3.0.0,>=2.114.1
Requires-Dist: constructs <11.0.0,>=10.3.0
Requires-Dist: jsii <2.0.0,>=1.93.0
Requires-Dist: publication >=0.0.3
Requires-Dist: typeguard ~=2.13.3
